dddmisc_rmq/__init__.py
dddmisc_rmq/events_transport/__init__.py
dddmisc_rmq/events_transport/consumer.py
dddmisc_rmq/events_transport/publisher.py
dddmisc_rmq/events_transport/transports.py
ddd_misc_rabbitmq_transport-0.2.0.dist-info/METADATA
ddd_misc_rabbitmq_transport-0.2.0.dist-info/WHEEL
ddd_misc_rabbitmq_transport-0.2.0.dist-info/RECORD
