Metadata-Version: 2.1
Name: ddd-misc-rabbitmq-transport
Version: 0.2.0
Summary: 
Author: Vladislav Vorobyov
Author-email: vladislav.vorobyov@gmail.com
Requires-Python: >=3.8,<4.0
Classifier: Programming Language :: Python :: 3
Classifier: Programming Language :: Python :: 3.8
Classifier: Programming Language :: Python :: 3.9
Classifier: Programming Language :: Python :: 3.10
Classifier: Programming Language :: Python :: 3.11
Requires-Dist: aio-pika (>=8.0.3,<9.0.0)
Requires-Dist: ddd-misc (>=0.8.1,<0.9.0)
Requires-Dist: python-environ (>=0.4.54,<0.5.0)
